oiiai/__init__.py
oiiai/fetchModelList/__base__.py
oiiai/fetchModelList/__factory__.py
oiiai/fetchModelList/__init__.py
oiiai/fetchModelList/__log_config__.py
oiiai/fetchModelList/chutes.py
oiiai/fetchModelList/groq.py
oiiai/fetchModelList/iflow.py
oiiai/fetchModelList/modelscope.py
oiiai/fetchModelList/nova.py
oiiai/fetchModelList/openrouter.py
oiiai/fetchModelList/siliconflow.py
oiiai/fetchModelList/zenmux.py
oiiai/fetchModelList/zhipu.py
oiiai_lib-0.0.7.dist-info/METADATA
oiiai_lib-0.0.7.dist-info/WHEEL
oiiai_lib-0.0.7.dist-info/licenses/LICENSE
oiiai_lib-0.0.7.dist-info/RECORD
