Metadata-Version: 2.4
Name: oiiai-lib
Version: 0.0.7
Summary: A minimalist Python package scaffolded with uv
Project-URL: Homepage, https://github.com/weisiren000/oiiai
Project-URL: Repository, https://github.com/weisiren000/oiiai
Project-URL: Documentation, https://github.com/weisiren000/oiiai
Project-URL: Issues, https://github.com/weisiren000/oiiai/issues
Author-email: Chen Xuanyi <cxyvsir04@qq.com>
Maintainer-email: Chen Xuanyi <cxyvsir04@qq.com>
License: MIT
License-File: LICENSE
Classifier: Development Status :: 3 - Alpha
Classifier: Intended Audience :: Developers
Classifier: License :: OSI Approved :: MIT License
Classifier: Programming Language :: Python :: 3
Classifier: Programming Language :: Python :: 3.8
Classifier: Programming Language :: Python :: 3.9
Classifier: Programming Language :: Python :: 3.10
Classifier: Programming Language :: Python :: 3.11
Classifier: Programming Language :: Python :: 3.12
Classifier: Programming Language :: Python :: 3.13
Requires-Python: >=3.8
Requires-Dist: beautifulsoup4>=4.12.0
Requires-Dist: brotli>=1.2.0
Requires-Dist: lxml>=5.0.0
Requires-Dist: requests>=2.25.0
Requires-Dist: sniffio>=1.3.1
Requires-Dist: zhipuai>=2.0.0
Provides-Extra: dev
Requires-Dist: mypy>=1.0.0; extra == 'dev'
Requires-Dist: pytest>=7.0.0; extra == 'dev'
Requires-Dist: ruff>=0.1.0; extra == 'dev'
